SMC/smc.py
smcover-0.1.dist-info/LICENSE.txt
smcover-0.1.dist-info/METADATA
smcover-0.1.dist-info/WHEEL
smcover-0.1.dist-info/top_level.txt
smcover-0.1.dist-info/RECORD
