Metadata-Version: 2.1
Name: smcover
Version: 0.1
Summary: Determines the area, and probability of follow up campaigns for GW triggers
Home-page: https://github.com/ryanc123/GW_follow-upper
Author: Ry Cutter
Author-email: R.Cutter@warwick.ac.uk
License: GNU
Platform: UNKNOWN
